iacele/__init__.py
iacele/algoritmo_cobranza_mes.py
iacele/algoritmo_costo_ventas_mes.py
iacele/algoritmo_ventas_mes.py
iacele-0.0.3.dist-info/LICENSE
iacele-0.0.3.dist-info/METADATA
iacele-0.0.3.dist-info/WHEEL
iacele-0.0.3.dist-info/top_level.txt
iacele-0.0.3.dist-info/RECORD
