Metadata-Version: 2.1
Name: iacele
Version: 0.0.3
Summary: Librería para crear BI en la administración de la empresa LA CASA DEL CARPINTERO
Author-email: Emilio Costich Pérez <ecostichp@gmail.com>
License: MIT License
License-File: LICENSE
Requires-Dist: pandas
